README
setup.py
cocograph/__init__.py
cocograph/dialog_node.py
cocograph/tile_dialogs.py
cocograph/tile_layers.py
cocograph/tile_widgets.py
cocograph.egg-info/PKG-INFO
cocograph.egg-info/SOURCES.txt
cocograph.egg-info/dependency_links.txt
cocograph.egg-info/not-zip-safe
cocograph.egg-info/requires.txt
cocograph.egg-info/top_level.txt